pamela/__init__.py
pamela/app.py
pamela_lib-0.1.3.dist-info/LICENSE
pamela_lib-0.1.3.dist-info/METADATA
pamela_lib-0.1.3.dist-info/WHEEL
pamela_lib-0.1.3.dist-info/top_level.txt
pamela_lib-0.1.3.dist-info/RECORD
