Metadata-Version: 2.1
Name: pamela-lib
Version: 0.1.3
Summary: Pamela is a python library to simplify API usage in programs
Home-page: https://github.com/zlElo/Pamela
Author: zlElo
Author-email: mail@zlelo.de
License: MPL-2.0
Keywords: api,library,api-wrapper,simplify
Classifier: Intended Audience :: Developers
Classifier: Programming Language :: Python :: 3
Classifier: Operating System :: Unix
Classifier: Operating System :: MacOS :: MacOS X
Classifier: Operating System :: Microsoft :: Windows
License-File: LICENSE
